alibabacloud_hcs_mgw20240626/__init__.py
alibabacloud_hcs_mgw20240626/client.py
alibabacloud_hcs_mgw20240626/models.py
alibabacloud_hcs_mgw20240626-1.0.2.dist-info/LICENSE
alibabacloud_hcs_mgw20240626-1.0.2.dist-info/METADATA
alibabacloud_hcs_mgw20240626-1.0.2.dist-info/WHEEL
alibabacloud_hcs_mgw20240626-1.0.2.dist-info/top_level.txt
alibabacloud_hcs_mgw20240626-1.0.2.dist-info/RECORD
